dlabs/__init__.py
dlabs/client.py
dlabs/exceptions.py
dlabs.py-0.0.1.dist-info/LICENSE
dlabs.py-0.0.1.dist-info/METADATA
dlabs.py-0.0.1.dist-info/WHEEL
dlabs.py-0.0.1.dist-info/top_level.txt
dlabs.py-0.0.1.dist-info/RECORD
