Metadata-Version: 2.1
Name: dlabs.py
Version: 0.0.1
Summary: A simple, fully asynchronous wrapper for the Discord Labs API.
Home-page: https://github.com/itsmewulf/dlabs.py
Author: itsmewulf
Author-email: wulf.developer@gmail.com
License: UNKNOWN
Keywords: api-wrapper,http,request,api,wrapper,discord
Platform: UNKNOWN
Classifier: Programming Language :: Python :: 3
Classifier: License :: OSI Approved :: MIT License
Classifier: Operating System :: OS Independent
Requires-Python: >=3.6
